enn_iot_oc/__init__.py
enn_iot_oc/core/__init__.py
enn_iot_oc/infrastructure/__init__.py
enn_iot_oc/infrastructure/repository/__init__.py
enn_iot_oc/infrastructure/repository/multi_repo_base.py
enn_iot_oc/infrastructure/repository/single_repo_base.py
enn_iot_oc/util/__init__.py
enn_iot_oc/util/string_util.py
generator/__init__.py
generator/config_parser.py
generator/entity_generator.py
generator/mock_generator.py
generator/repository_generator.py
generator/type_inferencer.py
ioc_data_sdk/__init__.py
ioc_data_sdk/entities.py
ioc_data_sdk/repositories.py
ioc_data_sdk/core/__init__.py
ioc_data_sdk/data/relations.yaml
ioc_data_sdk/data/source/category_requirement.json
ioc_data_sdk/data/source/customer.json
ioc_data_sdk/data/source/customer_category.json
ioc_data_sdk/data/source/customer_profile.json
ioc_data_sdk/data/source/profile_dimension.json
ioc_data_sdk/infrastructure/__init__.py
ioc_data_sdk/infrastructure/repository/__init__.py
ioc_data_sdk/infrastructure/repository/multi_repo_base.py
ioc_data_sdk/infrastructure/repository/single_repo_base.py
ioc_data_sdk/util/__init__.py
ioc_data_sdk/util/string_util.py
output/__init__.py
output/test_relations.py
output/usage_example.py
output/infrastructure/__init__.py
output/infrastructure/model/CategoryRequirement.py
output/infrastructure/model/Customer.py
output/infrastructure/model/CustomerCategory.py
output/infrastructure/model/CustomerProfile.py
output/infrastructure/model/ProfileDimension.py
output/infrastructure/model/__init__.py
output_new/__init__.py
output_new/test_relations.py
output_new/usage_example.py
output_new/infrastructure/__init__.py
output_new/infrastructure/model/CategoryRequirement.py
output_new/infrastructure/model/Customer.py
output_new/infrastructure/model/CustomerCategory.py
output_new/infrastructure/model/CustomerProfile.py
output_new/infrastructure/model/ProfileDimension.py
output_new/infrastructure/model/__init__.py
enn_iot_oc_sdk-2.0.2.dist-info/METADATA
enn_iot_oc_sdk-2.0.2.dist-info/WHEEL
enn_iot_oc_sdk-2.0.2.dist-info/entry_points.txt
enn_iot_oc_sdk-2.0.2.dist-info/top_level.txt
enn_iot_oc_sdk-2.0.2.dist-info/RECORD
