Metadata-Version: 2.1
Name: enn-iot-oc-sdk
Version: 2.0.2
Summary: IoC数据SDK - 提供工业物联网数据查询接口
Home-page: https://github.com/enn-energy/enn-iot-oc-sdk
Author: ENN Energy
Author-email: developer@enn.com
Project-URL: Bug Reports, https://github.com/enn-energy/enn-iot-oc-sdk/issues
Project-URL: Source, https://github.com/enn-energy/enn-iot-oc-sdk
Project-URL: Documentation, https://github.com/enn-energy/enn-iot-oc-sdk/wiki
Keywords: iot,industrial,data,sdk,repository,query
Classifier: Development Status :: 4 - Beta
Classifier: Intended Audience :: Developers
Classifier: Topic :: Software Development :: Libraries :: Python Modules
Classifier: License :: OSI Approved :: MIT License
Classifier: Programming Language :: Python :: 3
Classifier: Programming Language :: Python :: 3.7
Classifier: Programming Language :: Python :: 3.8
Classifier: Programming Language :: Python :: 3.9
Classifier: Programming Language :: Python :: 3.10
Classifier: Programming Language :: Python :: 3.11
Classifier: Operating System :: OS Independent
Requires-Python: >=3.7
Requires-Dist: pyyaml>=6.0
Requires-Dist: dataclasses-json>=0.6.1
Requires-Dist: typing-inspect>=0.9.0
Provides-Extra: dev
Requires-Dist: pytest>=6.0; extra == "dev"
Requires-Dist: pytest-cov>=2.0; extra == "dev"
Requires-Dist: black>=21.0; extra == "dev"
Requires-Dist: flake8>=3.8; extra == "dev"
